dbml/__init__.py
dbml/ridge_causal_inference.py
causal_inference_regression-1.0.0.dist-info/METADATA
causal_inference_regression-1.0.0.dist-info/WHEEL
causal_inference_regression-1.0.0.dist-info/top_level.txt
causal_inference_regression-1.0.0.dist-info/RECORD
