Metadata-Version: 2.1
Name: causal-inference-regression
Version: 1.0.0
Summary: Causal inference with de-biased ML regression modelling
Home-page: https://github.com/jcatankard/DBML
Author: Josh Tankard
Requires-Dist: NumbaML
Requires-Dist: numpy
